honeybee_openstudio/__init__.py
honeybee_openstudio/__main__.py
honeybee_openstudio/_extend_honeybee.py
honeybee_openstudio/construction.py
honeybee_openstudio/constructionset.py
honeybee_openstudio/generator.py
honeybee_openstudio/internalmass.py
honeybee_openstudio/load.py
honeybee_openstudio/material.py
honeybee_openstudio/openstudio.py
honeybee_openstudio/programtype.py
honeybee_openstudio/reader.py
honeybee_openstudio/schedule.py
honeybee_openstudio/shw.py
honeybee_openstudio/simulation.py
honeybee_openstudio/ventcool.py
honeybee_openstudio/writer.py
honeybee_openstudio/cli/__init__.py
honeybee_openstudio/cli/translate.py
honeybee_openstudio/hvac/__init__.py
honeybee_openstudio/hvac/idealair.py
honeybee_openstudio/hvac/template.py
honeybee_openstudio/hvac/standards/__init__.py
honeybee_openstudio/hvac/standards/air_conditioner_variable_refrigerant_flow.py
honeybee_openstudio/hvac/standards/boiler_hot_water.py
honeybee_openstudio/hvac/standards/central_air_source_heat_pump.py
honeybee_openstudio/hvac/standards/coil_cooling.py
honeybee_openstudio/hvac/standards/coil_heating.py
honeybee_openstudio/hvac/standards/cooling_tower.py
honeybee_openstudio/hvac/standards/fan.py
honeybee_openstudio/hvac/standards/heat_recovery.py
honeybee_openstudio/hvac/standards/hvac_systems.py
honeybee_openstudio/hvac/standards/plant_loop.py
honeybee_openstudio/hvac/standards/pump_variable_speed.py
honeybee_openstudio/hvac/standards/radiant_system_controls.py
honeybee_openstudio/hvac/standards/schedule.py
honeybee_openstudio/hvac/standards/sizing_system.py
honeybee_openstudio/hvac/standards/thermal_zone.py
honeybee_openstudio/hvac/standards/utilities.py
honeybee_openstudio/hvac/standards/data/__init__.py
honeybee_openstudio/hvac/standards/data/ashrae_90_1.curves.json
honeybee_openstudio/hvac/standards/data/ashrae_90_1.fans.json
honeybee_openstudio-0.4.3.dist-info/licenses/LICENSE
honeybee_openstudio-0.4.3.dist-info/METADATA
honeybee_openstudio-0.4.3.dist-info/WHEEL
honeybee_openstudio-0.4.3.dist-info/entry_points.txt
honeybee_openstudio-0.4.3.dist-info/top_level.txt
honeybee_openstudio-0.4.3.dist-info/RECORD
