Metadata-Version: 2.4
Name: honeybee-openstudio
Version: 0.4.3
Summary: Honeybee extension for translating HBJSON models to OpenStudio (for OSM, IDF and gbXML).
Home-page: https://github.com/ladybug-tools/honeybee-openstudio
Author: Ladybug Tools
Author-email: info@ladybug.tools
License: AGPL-3.0
Classifier: Programming Language :: Python :: 3.7
Classifier: Programming Language :: Python :: 3.8
Classifier: Programming Language :: Python :: 3.9
Classifier: Programming Language :: Python :: 3.10
Classifier: Programming Language :: Python :: 3.11
Classifier: Programming Language :: Python :: 3.12
Classifier: Programming Language :: Python :: Implementation :: CPython
Classifier: Programming Language :: Python :: Implementation :: IronPython
Classifier: Operating System :: OS Independent
License-File: LICENSE
Requires-Dist: honeybee-energy>=1.116.106
Requires-Dist: openstudio==3.10.0
Provides-Extra: standards
Requires-Dist: honeybee-energy-standards==2.3.0; extra == "standards"
Dynamic: author
Dynamic: author-email
Dynamic: classifier
Dynamic: description
Dynamic: description-content-type
Dynamic: home-page
Dynamic: license
Dynamic: license-file
Dynamic: provides-extra
Dynamic: requires-dist
Dynamic: summary
